chensoul_hello/__init__.py
chensoul_hello/cli.py
hello_package/__init__.py
hello_package/cli.py
my_package/__init__.py
my_package/cli.py
chensoul_hello-1.0.0.dist-info/METADATA
chensoul_hello-1.0.0.dist-info/WHEEL
chensoul_hello-1.0.0.dist-info/entry_points.txt
chensoul_hello-1.0.0.dist-info/top_level.txt
chensoul_hello-1.0.0.dist-info/RECORD
