Metadata-Version: 2.1
Name: chensoul-hello
Version: 1.0.0
Summary: A simple Python package
Author: John Doe
Author-email: john.doe@example.com
Requires-Dist: numpy (>=1.16.0)
Requires-Dist: pandas (>=0.23.4)
